Metadata-Version: 2.1
Name: tango-comments
Version: 0.9.0
Summary: A simple port of the old django.contrib.comments into Tango.
Home-page: http://github.com/tBaxter/tango-comments
Author: Tim Baxter
Author-email: mail.baxter@gmail.com
License: LICENSE
Platform: UNKNOWN
Classifier: Development Status :: 4 - Beta
Classifier: Environment :: Web Environment
Classifier: Framework :: Django
Classifier: Intended Audience :: Developers
Classifier: License :: OSI Approved :: BSD License
Classifier: Operating System :: OS Independent
Classifier: Programming Language :: Python
Classifier: Topic :: Utilities
Requires-Dist: tango-shared-core (>=0.7)
